dgNova/__init__.py
dgNova/core/__init__.py
dgNova/core/analysis.py
dgNova/core/statistics.py
dgNova/field_designs/__init__.py
dgNova/field_designs/alpha_lattice.py
dgNova/field_designs/crd.py
dgNova/field_designs/latin_square.py
dgNova/field_designs/lattice.py
dgNova/field_designs/layouts.py
dgNova/field_designs/rcbd.py
dgNova/field_designs/replicated_design.py
dgNova/field_designs/split_plot.py
dgNova/field_designs/unreplicated_design.py
dgNova/io/__init__.py
dgNova/io/input.py
dgNova/io/output.py
dgNova/mating_designs/__init__.py
dgNova/mating_designs/diallel.py
dgNova/tests/__init__.py
dgNova/tests/test_io.py
dgNova/tests/test_unreplicated.py
dgNova-1.2.12.dist-info/LICENSE
dgNova-1.2.12.dist-info/METADATA
dgNova-1.2.12.dist-info/WHEEL
dgNova-1.2.12.dist-info/top_level.txt
dgNova-1.2.12.dist-info/RECORD
