Metadata-Version: 2.1
Name: dgNova
Version: 1.2.12
Summary: Statistical Analysis and Simulations for Plant Breeding Experiments
Home-page: https://github.com/nfornadimkhan/dgNova
Author: Nadim Khan
Author-email: nfornadim@gmail.com
License: MIT License
Classifier: License :: OSI Approved :: MIT License
Requires-Python: >=3.7
License-File: LICENSE
